{"owner":"python","name":"peps","url":"http://www.github.com/python/peps","language":"Python","nameconcat":"python/peps","script_execution":{"start_at":"00:08 25/10/2021","finished_at":"00:09 25/10/2021"},"id":13414105,"created_at":"2013-10-08T13:27:12Z","stars":2813,"subscribers":233,"watchers":2813,"forks":1062,"first_contribuitions":[{"login":"ncoghlan","created_at":"2021-10-24T14:44:36Z","issue_number":2124},{"login":"Rosuav","created_at":"2021-10-23T23:04:35Z","issue_number":2123},{"login":"snoyes","created_at":"2021-10-21T20:06:54Z","issue_number":2122},{"login":"vstinner","created_at":"2021-10-20T12:04:43Z","issue_number":2120},{"login":"erlend-aasland","created_at":"2021-10-19T23:11:29Z","issue_number":2116},{"login":"iritkatriel","created_at":"2021-10-19T17:02:44Z","issue_number":2113},{"login":"gvanrossum","created_at":"2021-10-18T23:58:25Z","issue_number":2112},{"login":"pablogsal","created_at":"2021-10-18T19:17:44Z","issue_number":2111},{"login":"jacobtylerwalls","created_at":"2021-10-17T13:46:23Z","issue_number":2110},{"login":"abitrolly","created_at":"2021-10-14T07:42:07Z","issue_number":2108},{"login":"warsaw","created_at":"2021-10-12T16:46:01Z","issue_number":2106},{"login":"srittau","created_at":"2021-10-08T20:51:28Z","issue_number":2105},{"login":"raulcd","created_at":"2021-10-05T10:43:49Z","issue_number":2101},{"login":"hugovk","created_at":"2021-10-05T09:12:45Z","issue_number":2099},{"login":"graingert","created_at":"2021-10-02T14:01:42Z","issue_number":2096},{"login":"taleinat","created_at":"2021-09-30T05:19:00Z","issue_number":2094},{"login":"tekumara","created_at":"2021-09-28T08:22:53Z","issue_number":2092},{"login":"AndreasChristianson","created_at":"2021-09-27T04:42:09Z","issue_number":2090},{"login":"rednafi","created_at":"2021-09-26T21:45:05Z","issue_number":2089},{"login":"xochozomatli","created_at":"2021-09-21T20:26:07Z","issue_number":2086},{"login":"freundTech","created_at":"2021-09-21T15:28:39Z","issue_number":2085},{"login":"nipunn1313","created_at":"2021-09-20T20:17:46Z","issue_number":2083},{"login":"DimitriPapadopoulos","created_at":"2021-09-19T20:37:08Z","issue_number":2082},{"login":"jdmarch","created_at":"2021-09-14T14:03:10Z","issue_number":2071},{"login":"markshannon","created_at":"2021-09-13T15:42:35Z","issue_number":2070},{"login":"ethanfurman","created_at":"2021-09-11T00:23:27Z","issue_number":2069},{"login":"jorenham","created_at":"2021-09-07T21:20:10Z","issue_number":2066},{"login":"DonnaDia","created_at":"2021-08-31T14:58:28Z","issue_number":2065},{"login":"moefear85","created_at":"2021-08-28T17:32:48Z","issue_number":2062},{"login":"PythonCHB","created_at":"2021-08-26T05:23:06Z","issue_number":2059},{"login":"geofft","created_at":"2021-08-25T20:57:13Z","issue_number":2058},{"login":"mrahtz","created_at":"2021-08-22T19:32:20Z","issue_number":2055},{"login":"uranusjr","created_at":"2021-08-18T04:02:00Z","issue_number":2050},{"login":"pradyunsg","created_at":"2021-08-17T17:59:05Z","issue_number":2049},{"login":"methane","created_at":"2021-08-07T08:46:21Z","issue_number":2047},{"login":"Yhg1s","created_at":"2021-08-06T14:06:09Z","issue_number":2046},{"login":"brettcannon","created_at":"2021-07-29T23:28:00Z","issue_number":2043},{"login":"vkbo","created_at":"2021-07-22T09:10:05Z","issue_number":2041},{"login":"ambv","created_at":"2021-07-21T12:25:48Z","issue_number":2040},{"login":"domdfcoding","created_at":"2021-07-14T16:43:07Z","issue_number":2034},{"login":"ammaraskar","created_at":"2021-07-12T20:42:03Z","issue_number":2032},{"login":"verhovsky","created_at":"2021-07-10T08:54:58Z","issue_number":2029},{"login":"jack1142","created_at":"2021-07-07T17:01:11Z","issue_number":2028},{"login":"SA-WS","created_at":"2021-07-06T00:55:49Z","issue_number":2027},{"login":"AA-Turner","created_at":"2021-07-04T16:57:25Z","issue_number":2024},{"login":"isidentical","created_at":"2021-07-04T08:41:19Z","issue_number":2022},{"login":"uriyyo","created_at":"2021-07-02T07:27:36Z","issue_number":2020},{"login":"corona10","created_at":"2021-07-01T03:10:03Z","issue_number":2018},{"login":"superbobry","created_at":"2021-06-29T11:40:46Z","issue_number":2013},{"login":"sbidoul","created_at":"2021-06-28T17:06:18Z","issue_number":2009},{"login":"gaborbernat","created_at":"2021-06-28T13:16:40Z","issue_number":2008},{"login":"KMChris","created_at":"2021-06-24T19:39:42Z","issue_number":2002},{"login":"brandtbucher","created_at":"2021-06-24T17:00:46Z","issue_number":2001},{"login":"bluebird75","created_at":"2021-06-21T19:54:50Z","issue_number":1997},{"login":"Mariatta","created_at":"2021-06-17T19:59:54Z","issue_number":1993},{"login":"zooba","created_at":"2021-06-11T22:01:54Z","issue_number":1990},{"login":"JulienPalard","created_at":"2021-06-07T12:35:30Z","issue_number":1985},{"login":"andresdelfino","created_at":"2021-06-06T14:10:22Z","issue_number":1981},{"login":"skirpichev","created_at":"2021-05-31T09:18:13Z","issue_number":1973},{"login":"Fidget-Spinner","created_at":"2021-05-23T15:19:32Z","issue_number":1968},{"login":"fredrikaverpil","created_at":"2021-05-15T18:44:39Z","issue_number":1963},{"login":"mayeut","created_at":"2021-05-13T13:06:48Z","issue_number":1962},{"login":"ankush","created_at":"2021-05-13T12:17:06Z","issue_number":1961},{"login":"matrixise","created_at":"2021-05-05T10:32:34Z","issue_number":1946},{"login":"Schweinepriester","created_at":"2021-05-04T11:09:52Z","issue_number":1945},{"login":"JelleZijlstra","created_at":"2021-05-01T17:27:05Z","issue_number":1942},{"login":"mariocj89","created_at":"2021-04-30T11:38:54Z","issue_number":1941},{"login":"encukou","created_at":"2021-04-20T13:55:22Z","issue_number":1929},{"login":"tiran","created_at":"2021-04-17T09:44:09Z","issue_number":1927},{"login":"vlad11148","created_at":"2021-04-14T08:23:41Z","issue_number":1926},{"login":"ztane","created_at":"2021-04-10T07:34:50Z","issue_number":1918},{"login":"east825","created_at":"2021-04-03T15:03:47Z","issue_number":1907},{"login":"ezio-melotti","created_at":"2021-04-02T03:44:15Z","issue_number":1905},{"login":"CAM-Gerlach","created_at":"2021-03-23T03:40:30Z","issue_number":1890},{"login":"nim65s","created_at":"2021-03-19T21:34:25Z","issue_number":1879},{"login":"takluyver","created_at":"2021-03-06T13:17:45Z","issue_number":1861},{"login":"brondsem","created_at":"2021-03-01T20:46:25Z","issue_number":1853},{"login":"sean-lockwood","created_at":"2021-02-27T21:49:57Z","issue_number":1849},{"login":"davidfstr","created_at":"2021-02-27T03:09:55Z","issue_number":1847},{"login":"di","created_at":"2021-02-26T20:49:16Z","issue_number":1845},{"login":"naren-apixio","created_at":"2021-02-26T07:42:20Z","issue_number":1843},{"login":"sweeneyde","created_at":"2021-02-23T19:19:06Z","issue_number":1837},{"login":"The-Compiler","created_at":"2021-02-23T10:47:20Z","issue_number":1835},{"login":"1st1","created_at":"2021-02-22T20:18:42Z","issue_number":1833},{"login":"erictraut","created_at":"2021-02-20T22:39:41Z","issue_number":1826},{"login":"EvanCarroll","created_at":"2021-02-14T23:55:47Z","issue_number":1817},{"login":"mdujava","created_at":"2021-02-13T12:59:45Z","issue_number":1815},{"login":"JimJJewett","created_at":"2021-02-11T19:18:39Z","issue_number":1813},{"login":"gusmonod","created_at":"2021-02-09T11:30:40Z","issue_number":1808},{"login":"stefanoborini","created_at":"2021-02-06T17:58:46Z","issue_number":1800},{"login":"intgr","created_at":"2021-01-30T15:07:28Z","issue_number":1789},{"login":"crwilcox","created_at":"2021-01-29T22:26:18Z","issue_number":1786},{"login":"kpfleming","created_at":"2021-01-25T12:22:19Z","issue_number":1780},{"login":"bangseongbeom","created_at":"2021-01-03T02:53:27Z","issue_number":1755},{"login":"timgates42","created_at":"2020-12-28T00:52:03Z","issue_number":1749},{"login":"pxeger","created_at":"2020-12-24T11:38:22Z","issue_number":1746},{"login":"ewdurbin","created_at":"2020-12-16T13:11:31Z","issue_number":1739},{"login":"greatestape","created_at":"2020-12-15T23:01:09Z","issue_number":1738},{"login":"brainwane","created_at":"2020-12-14T15:37:21Z","issue_number":1732},{"login":"mdamien","created_at":"2020-12-08T14:13:28Z","issue_number":1728},{"login":"felixxm","created_at":"2020-12-04T09:26:31Z","issue_number":1727},{"login":"eumiro","created_at":"2020-12-04T06:40:37Z","issue_number":1726},{"login":"pganssle","created_at":"2020-12-01T14:58:02Z","issue_number":1724},{"login":"pfmoore","created_at":"2020-11-17T16:22:18Z","issue_number":1719},{"login":"chrahunt","created_at":"2020-11-16T14:49:49Z","issue_number":1716},{"login":"mnm678","created_at":"2020-11-10T22:25:24Z","issue_number":1711},{"login":"MaggieMoss","created_at":"2020-11-06T22:04:08Z","issue_number":1707},{"login":"ericvsmith","created_at":"2020-11-02T22:19:01Z","issue_number":1705},{"login":"ofek","created_at":"2020-11-01T03:01:48Z","issue_number":1702},{"login":"serhiy-storchaka","created_at":"2020-10-31T10:05:28Z","issue_number":1699},{"login":"dmoisset","created_at":"2020-10-23T11:28:05Z","issue_number":1678},{"login":"gpshead","created_at":"2020-10-22T22:59:26Z","issue_number":1674},{"login":"aeros","created_at":"2020-10-22T02:10:54Z","issue_number":1670},{"login":"pombredanne","created_at":"2020-10-16T18:03:54Z","issue_number":1656},{"login":"kadler","created_at":"2020-10-16T17:45:26Z","issue_number":1655},{"login":"rebcabin","created_at":"2020-10-16T16:21:00Z","issue_number":1654},{"login":"pochmann","created_at":"2020-10-09T14:46:34Z","issue_number":1643},{"login":"davisschenk","created_at":"2020-10-09T09:42:52Z","issue_number":1642},{"login":"gerritholl","created_at":"2020-10-06T15:10:51Z","issue_number":1640},{"login":"mbarkhau","created_at":"2020-10-05T20:15:10Z","issue_number":1638},{"login":"EpicWink","created_at":"2020-10-05T06:01:09Z","issue_number":1637},{"login":"waadnakhleh","created_at":"2020-10-02T06:31:45Z","issue_number":1634},{"login":"torsava","created_at":"2020-10-01T09:15:29Z","issue_number":1632},{"login":"tipabu","created_at":"2020-10-01T05:47:20Z","issue_number":1631},{"login":"adamchainz","created_at":"2020-09-26T08:08:26Z","issue_number":1621},{"login":"eric-wieser","created_at":"2020-09-25T08:15:22Z","issue_number":1618},{"login":"smurfix","created_at":"2020-09-24T10:38:53Z","issue_number":1615},{"login":"cryvate","created_at":"2020-09-23T23:43:16Z","issue_number":1614},{"login":"xavfernandez","created_at":"2020-09-21T20:14:08Z","issue_number":1611},{"login":"kevinfjbecker","created_at":"2020-09-15T09:40:54Z","issue_number":1599},{"login":"david-a-wheeler","created_at":"2020-09-08T03:10:20Z","issue_number":1590},{"login":"OrangeDog","created_at":"2020-09-07T12:34:11Z","issue_number":1586},{"login":"cool-RR","created_at":"2020-09-05T11:24:00Z","issue_number":1584},{"login":"wyz23x2","created_at":"2020-08-12T13:57:46Z","issue_number":1559},{"login":"shoyer","created_at":"2020-08-11T02:17:45Z","issue_number":1557},{"login":"jivthesh","created_at":"2020-08-04T06:12:06Z","issue_number":1548},{"login":"mrkmndz","created_at":"2020-07-31T23:07:49Z","issue_number":1546},{"login":"KOLANICH","created_at":"2020-07-29T17:47:28Z","issue_number":1542},{"login":"dstufft","created_at":"2020-07-17T08:43:44Z","issue_number":1530},{"login":"RMJ10","created_at":"2020-07-15T18:42:11Z","issue_number":1526},{"login":"viridia","created_at":"2020-07-08T01:35:31Z","issue_number":1504},{"login":"y9k8i","created_at":"2020-06-30T23:30:00Z","issue_number":1486},{"login":"thautwarm","created_at":"2020-06-27T08:01:23Z","issue_number":1473},{"login":"KearaBerlin","created_at":"2020-06-26T22:00:59Z","issue_number":1470},{"login":"Delta456","created_at":"2020-06-24T05:09:24Z","issue_number":1460},{"login":"jugmac00","created_at":"2020-06-23T19:19:02Z","issue_number":1456},{"login":"obestwalter","created_at":"2020-06-23T17:21:48Z","issue_number":1452},{"login":"willingc","created_at":"2020-06-22T14:22:25Z","issue_number":1445},{"login":"wimglenn","created_at":"2020-06-20T06:05:27Z","issue_number":1443},{"login":"AmaMidzu","created_at":"2020-06-18T23:15:09Z","issue_number":1439},{"login":"mcolen","created_at":"2020-06-03T19:51:59Z","issue_number":1421},{"login":"5j9","created_at":"2020-06-01T20:14:05Z","issue_number":1420},{"login":"DavidMertz","created_at":"2020-05-19T20:40:19Z","issue_number":1409},{"login":"mgedmin","created_at":"2020-05-19T18:18:17Z","issue_number":1408},{"login":"sarfatis","created_at":"2020-05-16T15:42:55Z","issue_number":1403},{"login":"rolf-d2i","created_at":"2020-05-08T12:02:52Z","issue_number":1397},{"login":"eyalho","created_at":"2020-05-06T20:09:01Z","issue_number":1396},{"login":"ericsnowcurrently","created_at":"2020-05-05T15:52:12Z","issue_number":1394},{"login":"jimm-domingo","created_at":"2020-05-05T01:04:30Z","issue_number":1393},{"login":"gstein","created_at":"2020-04-21T18:02:27Z","issue_number":1379},{"login":"lysnikolaou","created_at":"2020-04-17T18:12:05Z","issue_number":1372},{"login":"cdjc","created_at":"2020-04-16T02:30:34Z","issue_number":1370},{"login":"bskinn","created_at":"2020-04-13T22:05:39Z","issue_number":1365},{"login":"jeff5","created_at":"2020-04-06T20:49:07Z","issue_number":1363},{"login":"furkanonder","created_at":"2020-04-01T20:12:54Z","issue_number":1354},{"login":"hanifbirgani","created_at":"2020-03-25T20:31:10Z","issue_number":1342},{"login":"jheiv","created_at":"2020-03-24T07:34:05Z","issue_number":1339},{"login":"arunpersaud","created_at":"2020-03-23T04:39:38Z","issue_number":1338},{"login":"xmunoz","created_at":"2020-03-12T00:42:16Z","issue_number":1329},{"login":"lukpueh","created_at":"2020-03-05T10:33:59Z","issue_number":1326},{"login":"ganeshkbhat","created_at":"2020-03-04T03:24:20Z","issue_number":1325},{"login":"note35","created_at":"2020-02-28T07:05:49Z","issue_number":1321},{"login":"ethanhs","created_at":"2020-02-25T04:09:26Z","issue_number":1318},{"login":"merwok","created_at":"2020-02-15T14:51:17Z","issue_number":1307},{"login":"trishankatdatadog","created_at":"2020-02-04T00:41:51Z","issue_number":1295},{"login":"birkenfeld","created_at":"2020-02-03T06:51:19Z","issue_number":1293},{"login":"shannonzhu","created_at":"2020-01-31T19:19:53Z","issue_number":1291},{"login":"fried","created_at":"2020-01-29T22:28:34Z","issue_number":1288},{"login":"dkg","created_at":"2020-01-29T17:25:24Z","issue_number":1287},{"login":"aragilar","created_at":"2020-01-28T03:17:02Z","issue_number":1286},{"login":"JonDevOps","created_at":"2020-01-10T06:09:31Z","issue_number":1272},{"login":"goutham","created_at":"2019-12-29T03:13:17Z","issue_number":1263},{"login":"cfbolz","created_at":"2019-12-23T19:12:04Z","issue_number":1262},{"login":"grimreaper","created_at":"2019-12-18T12:49:07Z","issue_number":1258},{"login":"Wael-Abouelwafa","created_at":"2019-12-15T11:33:24Z","issue_number":1256},{"login":"ferdnyc","created_at":"2019-12-15T01:05:06Z","issue_number":1255},{"login":"michael-k","created_at":"2019-11-20T12:30:25Z","issue_number":1238},{"login":"m-aciek","created_at":"2019-11-11T19:32:06Z","issue_number":1232},{"login":"dimitern","created_at":"2019-11-08T20:10:34Z","issue_number":1230},{"login":"samredai","created_at":"2019-11-06T15:40:20Z","issue_number":1222},{"login":"moltob","created_at":"2019-11-04T14:02:06Z","issue_number":1220},{"login":"pprados","created_at":"2019-10-31T13:30:32Z","issue_number":1219},{"login":"maggyero","created_at":"2019-10-29T15:41:52Z","issue_number":1217},{"login":"zhaofeng-shu33","created_at":"2019-10-19T00:41:03Z","issue_number":1210},{"login":"ShaynAli","created_at":"2019-10-16T22:15:43Z","issue_number":1208},{"login":"JustinCappos","created_at":"2019-10-16T14:25:00Z","issue_number":1207},{"login":"YannickJadoul","created_at":"2019-10-13T11:27:19Z","issue_number":1205},{"login":"jaraco","created_at":"2019-10-04T18:51:08Z","issue_number":1195},{"login":"njsmith","created_at":"2019-10-03T04:53:20Z","issue_number":1191},{"login":"veblush","created_at":"2019-09-27T16:14:13Z","issue_number":1180},{"login":"BartoszCki","created_at":"2019-09-26T10:56:24Z","issue_number":1176},{"login":"dpgeorge","created_at":"2019-09-23T03:08:25Z","issue_number":1174},{"login":"bmerry","created_at":"2019-09-22T12:33:11Z","issue_number":1172},{"login":"moshekaplan","created_at":"2019-09-17T20:59:34Z","issue_number":1169},{"login":"asottile","created_at":"2019-09-12T14:53:53Z","issue_number":1166},{"login":"PyGeek03","created_at":"2019-09-11T09:40:31Z","issue_number":1162},{"login":"scoder","created_at":"2019-09-10T11:29:55Z","issue_number":1159},{"login":"Harmon758","created_at":"2019-09-03T07:19:58Z","issue_number":1154},{"login":"hdiogenes","created_at":"2019-08-30T15:33:13Z","issue_number":1152},{"login":"kigawas","created_at":"2019-08-23T06:12:42Z","issue_number":1150},{"login":"Michael0x2a","created_at":"2019-08-21T22:34:52Z","issue_number":1149},{"login":"verygoodsoftwarenotvirus","created_at":"2019-08-14T19:24:35Z","issue_number":1147},{"login":"msabramo","created_at":"2019-08-14T15:25:00Z","issue_number":1146},{"login":"minho42","created_at":"2019-08-11T14:07:58Z","issue_number":1144},{"login":"sergunya","created_at":"2019-08-10T20:23:38Z","issue_number":1143},{"login":"ghost","created_at":"2019-07-30T16:48:07Z","issue_number":1135},{"login":"native-api","created_at":"2019-07-24T08:47:57Z","issue_number":1131},{"login":"Jamim","created_at":"2019-06-25T14:29:13Z","issue_number":1112},{"login":"chris-martin","created_at":"2019-06-24T23:58:52Z","issue_number":1110},{"login":"Ben-KC","created_at":"2019-06-15T02:53:32Z","issue_number":1107},{"login":"pzrq","created_at":"2019-06-14T03:00:46Z","issue_number":1106},{"login":"tifv","created_at":"2019-06-12T13:30:12Z","issue_number":1104},{"login":"b0g3r","created_at":"2019-06-11T12:48:14Z","issue_number":1101},{"login":"ilevkivskyi","created_at":"2019-06-02T22:00:28Z","issue_number":1096},{"login":"pitrou","created_at":"2019-05-26T15:19:49Z","issue_number":1089},{"login":"Nightblade","created_at":"2019-05-22T10:22:39Z","issue_number":1075},{"login":"jjbankert","created_at":"2019-05-22T09:48:56Z","issue_number":1074},{"login":"JukkaL","created_at":"2019-05-20T16:45:51Z","issue_number":1060},{"login":"tsuyukimakoto","created_at":"2019-05-19T08:03:23Z","issue_number":1058},{"login":"jdemeyer","created_at":"2019-05-18T20:28:03Z","issue_number":1057},{"login":"brunocampos01","created_at":"2019-05-16T03:58:23Z","issue_number":1053},{"login":"msullivan","created_at":"2019-05-10T23:23:52Z","issue_number":1044},{"login":"larryhastings","created_at":"2019-05-09T22:03:04Z","issue_number":1040},{"login":"dkgi","created_at":"2019-05-08T05:33:25Z","issue_number":1033},{"login":"loganasherjones","created_at":"2019-05-06T15:19:36Z","issue_number":1024},{"login":"Carreau","created_at":"2019-05-02T03:10:51Z","issue_number":1021},{"login":"till-varoquaux","created_at":"2019-04-26T21:17:48Z","issue_number":1014},{"login":"vpoulailleau","created_at":"2019-04-17T06:15:29Z","issue_number":999},{"login":"hroncok","created_at":"2019-04-12T14:53:02Z","issue_number":989},{"login":"mozillazg","created_at":"2019-04-09T14:58:23Z","issue_number":982},{"login":"jameshamm","created_at":"2019-04-09T12:06:15Z","issue_number":981},{"login":"nyanpasu64","created_at":"2019-04-04T12:53:04Z","issue_number":974},{"login":"ericvw","created_at":"2019-04-03T15:16:51Z","issue_number":972},{"login":"RazerM","created_at":"2019-03-30T18:33:31Z","issue_number":966},{"login":"mcfarke311","created_at":"2019-03-29T21:32:07Z","issue_number":964},{"login":"cameron-simpson","created_at":"2019-03-19T22:35:00Z","issue_number":940},{"login":"EmilStenstrom","created_at":"2019-03-17T13:31:17Z","issue_number":937},{"login":"RDIL","created_at":"2019-03-12T12:38:24Z","issue_number":924},{"login":"johnsonb2","created_at":"2019-03-07T01:10:11Z","issue_number":914},{"login":"drtyrsa","created_at":"2019-03-04T09:24:33Z","issue_number":908},{"login":"Bharat123rox","created_at":"2019-02-15T04:03:58Z","issue_number":895},{"login":"tacaswell","created_at":"2019-02-14T16:20:32Z","issue_number":894},{"login":"james-emerton","created_at":"2019-01-27T22:23:15Z","issue_number":886},{"login":"emilyemorehouse","created_at":"2019-01-16T19:06:24Z","issue_number":876},{"login":"justinshenk","created_at":"2019-01-12T20:32:15Z","issue_number":874},{"login":"cjerdonek","created_at":"2019-01-10T01:02:29Z","issue_number":870},{"login":"sblondon","created_at":"2019-01-04T16:19:44Z","issue_number":864},{"login":"0101011","created_at":"2019-01-01T15:26:32Z","issue_number":861},{"login":"meysam81","created_at":"2018-12-28T06:00:36Z","issue_number":860},{"login":"doismellburning","created_at":"2018-12-10T15:55:31Z","issue_number":851},{"login":"benjaminp","created_at":"2018-12-07T19:27:11Z","issue_number":849},{"login":"freddrake","created_at":"2018-11-30T15:39:49Z","issue_number":847},{"login":"ssbr","created_at":"2018-11-22T06:16:25Z","issue_number":842},{"login":"jackjansen","created_at":"2018-11-09T13:51:38Z","issue_number":836},{"login":"dracos","created_at":"2018-11-05T15:15:42Z","issue_number":832},{"login":"ExplodingCabbage","created_at":"2018-10-28T20:29:54Z","issue_number":820},{"login":"danishprakash","created_at":"2018-10-23T12:07:49Z","issue_number":812},{"login":"qwhex","created_at":"2018-10-04T11:36:38Z","issue_number":798},{"login":"AYIDouble","created_at":"2018-09-23T12:54:43Z","issue_number":790},{"login":"yaseppochi","created_at":"2018-09-22T07:07:23Z","issue_number":789},{"login":"ssbarnea","created_at":"2018-09-19T15:31:44Z","issue_number":785},{"login":"kushaldas","created_at":"2018-09-13T19:09:31Z","issue_number":776},{"login":"berkerpeksag","created_at":"2018-09-11T21:32:00Z","issue_number":771},{"login":"expobrain","created_at":"2018-09-06T16:43:53Z","issue_number":767},{"login":"dhellmann","created_at":"2018-08-29T12:34:12Z","issue_number":766},{"login":"zware","created_at":"2018-08-29T02:26:26Z","issue_number":765},{"login":"eli-b","created_at":"2018-08-12T12:15:33Z","issue_number":756},{"login":"cben","created_at":"2018-08-02T09:28:16Z","issue_number":753},{"login":"cclauss","created_at":"2018-07-26T15:37:09Z","issue_number":748},{"login":"giampaolo","created_at":"2018-07-10T23:00:03Z","issue_number":733},{"login":"tim-one","created_at":"2018-07-10T21:13:57Z","issue_number":732},{"login":"delimitry","created_at":"2018-07-10T20:57:11Z","issue_number":730},{"login":"jcgoble3","created_at":"2018-07-10T02:24:21Z","issue_number":715},{"login":"NestorTejero","created_at":"2018-07-05T07:33:40Z","issue_number":694},{"login":"nascheme","created_at":"2018-07-03T18:32:23Z","issue_number":691},{"login":"selik","created_at":"2018-07-02T10:28:53Z","issue_number":690},{"login":"dongweiming","created_at":"2018-06-27T13:53:25Z","issue_number":688},{"login":"4383","created_at":"2018-06-25T22:09:28Z","issue_number":686},{"login":"enterprisey","created_at":"2018-06-14T05:38:28Z","issue_number":672},{"login":"jakevdp","created_at":"2018-06-04T14:38:00Z","issue_number":669},{"login":"Mizux","created_at":"2018-05-30T19:47:26Z","issue_number":666},{"login":"daxm","created_at":"2018-05-16T22:14:25Z","issue_number":657},{"login":"elprans","created_at":"2018-05-14T21:01:28Z","issue_number":648},{"login":"egaudry","created_at":"2018-05-04T13:28:06Z","issue_number":641},{"login":"zhsj","created_at":"2018-05-03T09:59:15Z","issue_number":639},{"login":"cshuaimin","created_at":"2018-04-30T09:23:36Z","issue_number":636},{"login":"jseakle","created_at":"2018-04-23T16:56:24Z","issue_number":628},{"login":"yoavcaspi","created_at":"2018-04-21T19:03:37Z","issue_number":627},{"login":"ogrisel","created_at":"2018-04-20T14:14:39Z","issue_number":625},{"login":"Dormouse759","created_at":"2018-04-12T15:07:18Z","issue_number":618},{"login":"nagataaaas","created_at":"2018-04-11T11:21:44Z","issue_number":615},{"login":"toonarmycaptain","created_at":"2018-04-10T16:50:09Z","issue_number":614},{"login":"markrwilliams","created_at":"2018-04-08T08:43:21Z","issue_number":612},{"login":"petered","created_at":"2018-04-05T16:11:44Z","issue_number":609},{"login":"neerajbadlani","created_at":"2018-04-01T21:37:03Z","issue_number":604},{"login":"Recursing","created_at":"2018-03-30T19:55:04Z","issue_number":603},{"login":"MarkMangoba","created_at":"2018-03-23T16:31:19Z","issue_number":599},{"login":"zhangyangyu","created_at":"2018-03-02T08:16:07Z","issue_number":585},{"login":"valsorym","created_at":"2018-02-27T22:17:55Z","issue_number":583},{"login":"mingrammer","created_at":"2018-02-22T07:08:50Z","issue_number":580},{"login":"davejagoda","created_at":"2018-02-14T19:02:00Z","issue_number":573},{"login":"VanL","created_at":"2018-02-07T14:19:45Z","issue_number":571},{"login":"mikesep","created_at":"2018-01-29T15:07:29Z","issue_number":563},{"login":"cosven","created_at":"2018-01-18T01:15:26Z","issue_number":549},{"login":"carltyndall","created_at":"2018-01-17T22:23:30Z","issue_number":545},{"login":"martinbroadhurst","created_at":"2017-12-31T18:34:16Z","issue_number":528},{"login":"jhertel","created_at":"2017-12-20T15:56:18Z","issue_number":518},{"login":"jamesray1","created_at":"2017-12-19T15:15:25Z","issue_number":517},{"login":"jsalter","created_at":"2017-12-16T20:50:25Z","issue_number":516},{"login":"ChrisBarker-NOAA","created_at":"2017-12-15T20:46:48Z","issue_number":514},{"login":"Janzert","created_at":"2017-12-14T23:31:24Z","issue_number":513},{"login":"nsoranzo","created_at":"2017-12-06T15:19:45Z","issue_number":494},{"login":"Naddiseo","created_at":"2017-12-04T21:46:15Z","issue_number":489},{"login":"westurner","created_at":"2017-11-30T11:18:12Z","issue_number":488},{"login":"jrheard","created_at":"2017-11-26T01:47:48Z","issue_number":482},{"login":"JCWDFCS","created_at":"2017-11-10T00:56:55Z","issue_number":457},{"login":"benhoyt","created_at":"2017-11-03T21:58:47Z","issue_number":448},{"login":"phdru","created_at":"2017-10-27T19:35:26Z","issue_number":444},{"login":"michaelplaing","created_at":"2017-10-27T19:10:15Z","issue_number":443},{"login":"ma8ma","created_at":"2017-10-23T21:23:01Z","issue_number":436},{"login":"jwilk","created_at":"2017-10-22T10:06:36Z","issue_number":435},{"login":"domnikkk","created_at":"2017-10-20T10:18:15Z","issue_number":434},{"login":"Naereen","created_at":"2017-10-18T08:56:02Z","issue_number":432},{"login":"wangqr","created_at":"2017-10-16T04:35:48Z","issue_number":429},{"login":"johnyf","created_at":"2017-09-28T12:45:47Z","issue_number":427},{"login":"joernheissler","created_at":"2017-09-10T13:49:54Z","issue_number":413},{"login":"k7hoven","created_at":"2017-09-06T10:04:59Z","issue_number":391},{"login":"bitdancer","created_at":"2017-09-05T22:51:26Z","issue_number":390},{"login":"embray","created_at":"2017-08-31T12:40:55Z","issue_number":382},{"login":"XKIRA1313","created_at":"2017-08-30T00:51:20Z","issue_number":380},{"login":"dvarrazzo","created_at":"2017-08-25T14:46:59Z","issue_number":374},{"login":"filipochnik","created_at":"2017-08-18T13:19:32Z","issue_number":354},{"login":"dianaclarke","created_at":"2017-08-14T22:38:52Z","issue_number":343},{"login":"jwodder","created_at":"2017-08-13T19:37:19Z","issue_number":341},{"login":"iustin","created_at":"2017-08-12T13:56:20Z","issue_number":339},{"login":"sureshvv","created_at":"2017-08-12T07:03:40Z","issue_number":338},{"login":"chicheng","created_at":"2017-08-08T05:21:10Z","issue_number":317},{"login":"matthiaskramm","created_at":"2017-07-07T18:23:58Z","issue_number":302},{"login":"lelit","created_at":"2017-06-17T16:06:07Z","issue_number":295},{"login":"JDongian","created_at":"2017-06-16T19:33:42Z","issue_number":294},{"login":"csabella","created_at":"2017-06-15T17:28:44Z","issue_number":293},{"login":"ismail-s","created_at":"2017-06-03T17:40:15Z","issue_number":282},{"login":"Lukasa","created_at":"2017-06-01T16:27:15Z","issue_number":278},{"login":"dashmug","created_at":"2017-05-16T09:18:24Z","issue_number":260},{"login":"DimitrisJim","created_at":"2017-05-15T17:59:08Z","issue_number":258},{"login":"pkch","created_at":"2017-05-12T19:52:01Z","issue_number":254},{"login":"pelme","created_at":"2017-05-08T19:32:21Z","issue_number":253},{"login":"sixolet","created_at":"2017-04-19T06:30:13Z","issue_number":242},{"login":"vphilippon","created_at":"2017-04-08T19:17:21Z","issue_number":240},{"login":"orenmn","created_at":"2017-03-14T16:10:58Z","issue_number":225},{"login":"alexmv","created_at":"2017-03-08T01:38:53Z","issue_number":220},{"login":"rjkmurray","created_at":"2017-02-20T04:55:17Z","issue_number":214},{"login":"Mayzie","created_at":"2017-02-14T03:49:08Z","issue_number":213},{"login":"louisrawlins","created_at":"2017-02-11T05:22:03Z","issue_number":206},{"login":"Mahi","created_at":"2017-02-10T14:51:21Z","issue_number":205},{"login":"knarfeh","created_at":"2017-02-02T13:51:20Z","issue_number":197},{"login":"tvieira","created_at":"2017-01-30T10:07:34Z","issue_number":192},{"login":"diraol","created_at":"2017-01-19T17:52:26Z","issue_number":185},{"login":"brucepucci","created_at":"2017-01-19T04:18:19Z","issue_number":183},{"login":"ybroze","created_at":"2017-01-16T17:21:41Z","issue_number":181},{"login":"nicknystrom","created_at":"2017-01-10T21:40:24Z","issue_number":178},{"login":"alexwlchan","created_at":"2017-01-04T22:28:21Z","issue_number":172},{"login":"amPerl","created_at":"2016-12-20T14:18:37Z","issue_number":162},{"login":"flying-sheep","created_at":"2016-12-10T14:13:05Z","issue_number":155},{"login":"xZise","created_at":"2016-10-26T13:38:27Z","issue_number":122},{"login":"mehaase","created_at":"2016-10-18T19:48:50Z","issue_number":119},{"login":"JelteF","created_at":"2016-10-09T10:55:59Z","issue_number":113},{"login":"rowillia","created_at":"2016-09-19T19:17:03Z","issue_number":106},{"login":"asvetlov","created_at":"2016-09-19T16:41:09Z","issue_number":105},{"login":"scop","created_at":"2016-09-19T10:41:11Z","issue_number":104},{"login":"ryanhiebert","created_at":"2016-09-08T21:09:09Z","issue_number":98},{"login":"sloanlance","created_at":"2016-09-03T08:39:51Z","issue_number":87},{"login":"tharvik","created_at":"2016-08-03T08:51:24Z","issue_number":67},{"login":"tecki","created_at":"2016-07-17T11:12:15Z","issue_number":57},{"login":"hexum","created_at":"2016-06-30T11:33:10Z","issue_number":42},{"login":"controversial","created_at":"2016-06-28T19:30:46Z","issue_number":40},{"login":"orsenthil","created_at":"2016-06-26T05:33:53Z","issue_number":37},{"login":"IanLee1521","created_at":"2016-06-25T19:34:05Z","issue_number":36},{"login":"timofurrer","created_at":"2016-06-17T23:10:02Z","issue_number":15}],"weekly_distribuition":[{"week":"41 2013","total":0,"dates":[]},{"week":"42 2013","total":0,"dates":[]},{"week":"43 2013","total":0,"dates":[]},{"week":"44 2013","total":0,"dates":[]},{"week":"45 2013","total":0,"dates":[]},{"week":"46 2013","total":0,"dates":[]},{"week":"47 2013","total":0,"dates":[]},{"week":"48 2013","total":0,"dates":[]},{"week":"49 2013","total":0,"dates":[]},{"week":"50 2013","total":0,"dates":[]},{"week":"51 2013","total":0,"dates":[]},{"week":"52 2013","total":0,"dates":[]},{"week":"01 2014","total":0,"dates":[]},{"week":"02 2014","total":0,"dates":[]},{"week":"03 2014","total":0,"dates":[]},{"week":"04 2014","total":0,"dates":[]},{"week":"05 2014","total":0,"dates":[]},{"week":"06 2014","total":0,"dates":[]},{"week":"07 2014","total":0,"dates":[]},{"week":"08 2014","total":0,"dates":[]},{"week":"09 2014","total":0,"dates":[]},{"week":"10 2014","total":0,"dates":[]},{"week":"11 2014","total":0,"dates":[]},{"week":"12 2014","total":0,"dates":[]},{"week":"13 2014","total":0,"dates":[]},{"week":"14 2014","total":0,"dates":[]},{"week":"15 2014","total":0,"dates":[]},{"week":"16 2014","total":0,"dates":[]},{"week":"17 2014","total":0,"dates":[]},{"week":"18 2014","total":0,"dates":[]},{"week":"19 2014","total":0,"dates":[]},{"week":"20 2014","total":0,"dates":[]},{"week":"21 2014","total":0,"dates":[]},{"week":"22 2014","total":0,"dates":[]},{"week":"23 2014","total":0,"dates":[]},{"week":"24 2014","total":0,"dates":[]},{"week":"25 2014","total":0,"dates":[]},{"week":"26 2014","total":0,"dates":[]},{"week":"27 2014","total":0,"dates":[]},{"week":"28 2014","total":0,"dates":[]},{"week":"29 2014","total":0,"dates":[]},{"week":"30 2014","total":0,"dates":[]},{"week":"31 2014","total":0,"dates":[]},{"week":"32 2014","total":0,"dates":[]},{"week":"33 2014","total":0,"dates":[]},{"week":"34 2014","total":0,"dates":[]},{"week":"35 2014","total":0,"dates":[]},{"week":"36 2014","total":0,"dates":[]},{"week":"37 2014","total":0,"dates":[]},{"week":"38 2014","total":0,"dates":[]},{"week":"39 2014","total":0,"dates":[]},{"week":"40 2014","total":0,"dates":[]},{"week":"41 2014","total":0,"dates":[]},{"week":"42 2014","total":0,"dates":[]},{"week":"43 2014","total":0,"dates":[]},{"week":"44 2014","total":0,"dates":[]},{"week":"45 2014","total":0,"dates":[]},{"week":"46 2014","total":0,"dates":[]},{"week":"47 2014","total":0,"dates":[]},{"week":"48 2014","total":0,"dates":[]},{"week":"49 2014","total":0,"dates":[]},{"week":"50 2014","total":0,"dates":[]},{"week":"51 2014","total":0,"dates":[]},{"week":"52 2014","total":0,"dates":[]},{"week":"01 2015","total":0,"dates":[]},{"week":"02 2015","total":0,"dates":[]},{"week":"03 2015","total":0,"dates":[]},{"week":"04 2015","total":0,"dates":[]},{"week":"05 2015","total":0,"dates":[]},{"week":"06 2015","total":0,"dates":[]},{"week":"07 2015","total":0,"dates":[]},{"week":"08 2015","total":0,"dates":[]},{"week":"09 2015","total":0,"dates":[]},{"week":"10 2015","total":0,"dates":[]},{"week":"11 2015","total":0,"dates":[]},{"week":"12 2015","total":0,"dates":[]},{"week":"13 2015","total":0,"dates":[]},{"week":"14 2015","total":0,"dates":[]},{"week":"15 2015","total":0,"dates":[]},{"week":"16 2015","total":0,"dates":[]},{"week":"17 2015","total":0,"dates":[]},{"week":"18 2015","total":0,"dates":[]},{"week":"19 2015","total":0,"dates":[]},{"week":"20 2015","total":0,"dates":[]},{"week":"21 2015","total":0,"dates":[]},{"week":"22 2015","total":0,"dates":[]},{"week":"23 2015","total":0,"dates":[]},{"week":"24 2015","total":0,"dates":[]},{"week":"25 2015","total":0,"dates":[]},{"week":"26 2015","total":0,"dates":[]},{"week":"27 2015","total":0,"dates":[]},{"week":"28 2015","total":0,"dates":[]},{"week":"29 2015","total":0,"dates":[]},{"week":"30 2015","total":0,"dates":[]},{"week":"31 2015","total":0,"dates":[]},{"week":"32 2015","total":0,"dates":[]},{"week":"33 2015","total":0,"dates":[]},{"week":"34 2015","total":0,"dates":[]},{"week":"35 2015","total":0,"dates":[]},{"week":"36 2015","total":0,"dates":[]},{"week":"37 2015","total":0,"dates":[]},{"week":"38 2015","total":0,"dates":[]},{"week":"39 2015","total":0,"dates":[]},{"week":"40 2015","total":0,"dates":[]},{"week":"41 2015","total":0,"dates":[]},{"week":"42 2015","total":0,"dates":[]},{"week":"43 2015","total":0,"dates":[]},{"week":"44 2015","total":0,"dates":[]},{"week":"45 2015","total":0,"dates":[]},{"week":"46 2015","total":0,"dates":[]},{"week":"47 2015","total":0,"dates":[]},{"week":"48 2015","total":0,"dates":[]},{"week":"49 2015","total":0,"dates":[]},{"week":"50 2015","total":0,"dates":[]},{"week":"51 2015","total":0,"dates":[]},{"week":"52 2015","total":0,"dates":[]},{"week":"53 2015","total":0,"dates":[]},{"week":"01 2016","total":0,"dates":[]},{"week":"02 2016","total":0,"dates":[]},{"week":"03 2016","total":0,"dates":[]},{"week":"04 2016","total":0,"dates":[]},{"week":"05 2016","total":0,"dates":[]},{"week":"06 2016","total":0,"dates":[]},{"week":"07 2016","total":0,"dates":[]},{"week":"08 2016","total":0,"dates":[]},{"week":"09 2016","total":0,"dates":[]},{"week":"10 2016","total":0,"dates":[]},{"week":"11 2016","total":0,"dates":[]},{"week":"12 2016","total":0,"dates":[]},{"week":"13 2016","total":0,"dates":[]},{"week":"14 2016","total":0,"dates":[]},{"week":"15 2016","total":0,"dates":[]},{"week":"16 2016","total":0,"dates":[]},{"week":"17 2016","total":0,"dates":[]},{"week":"18 2016","total":0,"dates":[]},{"week":"19 2016","total":0,"dates":[]},{"week":"20 2016","total":0,"dates":[]},{"week":"21 2016","total":0,"dates":[]},{"week":"22 2016","total":0,"dates":[]},{"week":"23 2016","total":0,"dates":[]},{"week":"24 2016","dates":["2016-06-17T23:10:02Z"],"total":1},{"week":"25 2016","dates":["2016-06-26T05:33:53Z","2016-06-25T19:34:05Z"],"total":2},{"week":"26 2016","dates":["2016-06-30T11:33:10Z","2016-06-28T19:30:46Z"],"total":2},{"week":"27 2016","total":0,"dates":[]},{"week":"28 2016","dates":["2016-07-17T11:12:15Z"],"total":1},{"week":"29 2016","total":0,"dates":[]},{"week":"30 2016","total":0,"dates":[]},{"week":"31 2016","dates":["2016-08-03T08:51:24Z"],"total":1},{"week":"32 2016","total":0,"dates":[]},{"week":"33 2016","total":0,"dates":[]},{"week":"34 2016","total":0,"dates":[]},{"week":"35 2016","dates":["2016-09-03T08:39:51Z"],"total":1},{"week":"36 2016","dates":["2016-09-08T21:09:09Z"],"total":1},{"week":"37 2016","total":0,"dates":[]},{"week":"38 2016","dates":["2016-09-19T19:17:03Z","2016-09-19T16:41:09Z","2016-09-19T10:41:11Z"],"total":3},{"week":"39 2016","total":0,"dates":[]},{"week":"40 2016","dates":["2016-10-09T10:55:59Z"],"total":1},{"week":"41 2016","total":0,"dates":[]},{"week":"42 2016","dates":["2016-10-18T19:48:50Z"],"total":1},{"week":"43 2016","dates":["2016-10-26T13:38:27Z"],"total":1},{"week":"44 2016","total":0,"dates":[]},{"week":"45 2016","total":0,"dates":[]},{"week":"46 2016","total":0,"dates":[]},{"week":"47 2016","total":0,"dates":[]},{"week":"48 2016","total":0,"dates":[]},{"week":"49 2016","dates":["2016-12-10T14:13:05Z"],"total":1},{"week":"50 2016","total":0,"dates":[]},{"week":"51 2016","dates":["2016-12-20T14:18:37Z"],"total":1},{"week":"52 2016","total":0,"dates":[]},{"week":"01 2017","dates":["2017-01-04T22:28:21Z"],"total":1},{"week":"02 2017","dates":["2017-01-10T21:40:24Z"],"total":1},{"week":"03 2017","dates":["2017-01-19T17:52:26Z","2017-01-19T04:18:19Z","2017-01-16T17:21:41Z"],"total":3},{"week":"04 2017","total":0,"dates":[]},{"week":"05 2017","dates":["2017-02-02T13:51:20Z","2017-01-30T10:07:34Z"],"total":2},{"week":"06 2017","dates":["2017-02-11T05:22:03Z","2017-02-10T14:51:21Z"],"total":2},{"week":"07 2017","dates":["2017-02-14T03:49:08Z"],"total":1},{"week":"08 2017","dates":["2017-02-20T04:55:17Z"],"total":1},{"week":"09 2017","total":0,"dates":[]},{"week":"10 2017","dates":["2017-03-08T01:38:53Z"],"total":1},{"week":"11 2017","dates":["2017-03-14T16:10:58Z"],"total":1},{"week":"12 2017","total":0,"dates":[]},{"week":"13 2017","total":0,"dates":[]},{"week":"14 2017","dates":["2017-04-08T19:17:21Z"],"total":1},{"week":"15 2017","total":0,"dates":[]},{"week":"16 2017","dates":["2017-04-19T06:30:13Z"],"total":1},{"week":"17 2017","total":0,"dates":[]},{"week":"18 2017","total":0,"dates":[]},{"week":"19 2017","dates":["2017-05-12T19:52:01Z","2017-05-08T19:32:21Z"],"total":2},{"week":"20 2017","dates":["2017-05-16T09:18:24Z","2017-05-15T17:59:08Z"],"total":2},{"week":"21 2017","total":0,"dates":[]},{"week":"22 2017","dates":["2017-06-03T17:40:15Z","2017-06-01T16:27:15Z"],"total":2},{"week":"23 2017","total":0,"dates":[]},{"week":"24 2017","dates":["2017-06-17T16:06:07Z","2017-06-16T19:33:42Z","2017-06-15T17:28:44Z"],"total":3},{"week":"25 2017","total":0,"dates":[]},{"week":"26 2017","total":0,"dates":[]},{"week":"27 2017","dates":["2017-07-07T18:23:58Z"],"total":1},{"week":"28 2017","total":0,"dates":[]},{"week":"29 2017","total":0,"dates":[]},{"week":"30 2017","total":0,"dates":[]},{"week":"31 2017","total":0,"dates":[]},{"week":"32 2017","dates":["2017-08-13T19:37:19Z","2017-08-12T13:56:20Z","2017-08-12T07:03:40Z","2017-08-08T05:21:10Z"],"total":4},{"week":"33 2017","dates":["2017-08-18T13:19:32Z","2017-08-14T22:38:52Z"],"total":2},{"week":"34 2017","dates":["2017-08-25T14:46:59Z"],"total":1},{"week":"35 2017","dates":["2017-08-31T12:40:55Z","2017-08-30T00:51:20Z"],"total":2},{"week":"36 2017","dates":["2017-09-10T13:49:54Z","2017-09-06T10:04:59Z","2017-09-05T22:51:26Z"],"total":3},{"week":"37 2017","total":0,"dates":[]},{"week":"38 2017","total":0,"dates":[]},{"week":"39 2017","dates":["2017-09-28T12:45:47Z"],"total":1},{"week":"40 2017","total":0,"dates":[]},{"week":"41 2017","total":0,"dates":[]},{"week":"42 2017","dates":["2017-10-22T10:06:36Z","2017-10-20T10:18:15Z","2017-10-18T08:56:02Z","2017-10-16T04:35:48Z"],"total":4},{"week":"43 2017","dates":["2017-10-27T19:35:26Z","2017-10-27T19:10:15Z","2017-10-23T21:23:01Z"],"total":3},{"week":"44 2017","dates":["2017-11-03T21:58:47Z"],"total":1},{"week":"45 2017","dates":["2017-11-10T00:56:55Z"],"total":1},{"week":"46 2017","total":0,"dates":[]},{"week":"47 2017","dates":["2017-11-26T01:47:48Z"],"total":1},{"week":"48 2017","dates":["2017-11-30T11:18:12Z"],"total":1},{"week":"49 2017","dates":["2017-12-06T15:19:45Z","2017-12-04T21:46:15Z"],"total":2},{"week":"50 2017","dates":["2017-12-16T20:50:25Z","2017-12-15T20:46:48Z","2017-12-14T23:31:24Z"],"total":3},{"week":"51 2017","dates":["2017-12-20T15:56:18Z","2017-12-19T15:15:25Z"],"total":2},{"week":"52 2017","dates":["2017-12-31T18:34:16Z"],"total":1},{"week":"01 2018","total":0,"dates":[]},{"week":"02 2018","total":0,"dates":[]},{"week":"03 2018","dates":["2018-01-18T01:15:26Z","2018-01-17T22:23:30Z"],"total":2},{"week":"04 2018","total":0,"dates":[]},{"week":"05 2018","dates":["2018-01-29T15:07:29Z"],"total":1},{"week":"06 2018","dates":["2018-02-07T14:19:45Z"],"total":1},{"week":"07 2018","dates":["2018-02-14T19:02:00Z"],"total":1},{"week":"08 2018","dates":["2018-02-22T07:08:50Z"],"total":1},{"week":"09 2018","dates":["2018-03-02T08:16:07Z","2018-02-27T22:17:55Z"],"total":2},{"week":"10 2018","total":0,"dates":[]},{"week":"11 2018","total":0,"dates":[]},{"week":"12 2018","dates":["2018-03-23T16:31:19Z"],"total":1},{"week":"13 2018","dates":["2018-04-01T21:37:03Z","2018-03-30T19:55:04Z"],"total":2},{"week":"14 2018","dates":["2018-04-08T08:43:21Z","2018-04-05T16:11:44Z"],"total":2},{"week":"15 2018","dates":["2018-04-12T15:07:18Z","2018-04-11T11:21:44Z","2018-04-10T16:50:09Z"],"total":3},{"week":"16 2018","dates":["2018-04-21T19:03:37Z","2018-04-20T14:14:39Z"],"total":2},{"week":"17 2018","dates":["2018-04-23T16:56:24Z"],"total":1},{"week":"18 2018","dates":["2018-05-04T13:28:06Z","2018-05-03T09:59:15Z","2018-04-30T09:23:36Z"],"total":3},{"week":"19 2018","total":0,"dates":[]},{"week":"20 2018","dates":["2018-05-16T22:14:25Z","2018-05-14T21:01:28Z"],"total":2},{"week":"21 2018","total":0,"dates":[]},{"week":"22 2018","dates":["2018-05-30T19:47:26Z"],"total":1},{"week":"23 2018","dates":["2018-06-04T14:38:00Z"],"total":1},{"week":"24 2018","dates":["2018-06-14T05:38:28Z"],"total":1},{"week":"25 2018","total":0,"dates":[]},{"week":"26 2018","dates":["2018-06-27T13:53:25Z","2018-06-25T22:09:28Z"],"total":2},{"week":"27 2018","dates":["2018-07-05T07:33:40Z","2018-07-03T18:32:23Z","2018-07-02T10:28:53Z"],"total":3},{"week":"28 2018","dates":["2018-07-10T23:00:03Z","2018-07-10T21:13:57Z","2018-07-10T20:57:11Z","2018-07-10T02:24:21Z"],"total":4},{"week":"29 2018","total":0,"dates":[]},{"week":"30 2018","dates":["2018-07-26T15:37:09Z"],"total":1},{"week":"31 2018","dates":["2018-08-02T09:28:16Z"],"total":1},{"week":"32 2018","dates":["2018-08-12T12:15:33Z"],"total":1},{"week":"33 2018","total":0,"dates":[]},{"week":"34 2018","total":0,"dates":[]},{"week":"35 2018","dates":["2018-08-29T12:34:12Z","2018-08-29T02:26:26Z"],"total":2},{"week":"36 2018","dates":["2018-09-06T16:43:53Z"],"total":1},{"week":"37 2018","dates":["2018-09-13T19:09:31Z","2018-09-11T21:32:00Z"],"total":2},{"week":"38 2018","dates":["2018-09-23T12:54:43Z","2018-09-22T07:07:23Z","2018-09-19T15:31:44Z"],"total":3},{"week":"39 2018","total":0,"dates":[]},{"week":"40 2018","dates":["2018-10-04T11:36:38Z"],"total":1},{"week":"41 2018","total":0,"dates":[]},{"week":"42 2018","total":0,"dates":[]},{"week":"43 2018","dates":["2018-10-28T20:29:54Z","2018-10-23T12:07:49Z"],"total":2},{"week":"44 2018","total":0,"dates":[]},{"week":"45 2018","dates":["2018-11-09T13:51:38Z","2018-11-05T15:15:42Z"],"total":2},{"week":"46 2018","total":0,"dates":[]},{"week":"47 2018","dates":["2018-11-22T06:16:25Z"],"total":1},{"week":"48 2018","dates":["2018-11-30T15:39:49Z"],"total":1},{"week":"49 2018","dates":["2018-12-07T19:27:11Z"],"total":1},{"week":"50 2018","dates":["2018-12-10T15:55:31Z"],"total":1},{"week":"51 2018","total":0,"dates":[]},{"week":"52 2018","dates":["2018-12-28T06:00:36Z"],"total":1},{"week":"01 2019","dates":["2019-01-04T16:19:44Z","2019-01-01T15:26:32Z"],"total":2},{"week":"02 2019","dates":["2019-01-12T20:32:15Z","2019-01-10T01:02:29Z"],"total":2},{"week":"03 2019","dates":["2019-01-16T19:06:24Z"],"total":1},{"week":"04 2019","dates":["2019-01-27T22:23:15Z"],"total":1},{"week":"05 2019","total":0,"dates":[]},{"week":"06 2019","total":0,"dates":[]},{"week":"07 2019","dates":["2019-02-15T04:03:58Z","2019-02-14T16:20:32Z"],"total":2},{"week":"08 2019","total":0,"dates":[]},{"week":"09 2019","total":0,"dates":[]},{"week":"10 2019","dates":["2019-03-07T01:10:11Z","2019-03-04T09:24:33Z"],"total":2},{"week":"11 2019","dates":["2019-03-17T13:31:17Z","2019-03-12T12:38:24Z"],"total":2},{"week":"12 2019","dates":["2019-03-19T22:35:00Z"],"total":1},{"week":"13 2019","dates":["2019-03-30T18:33:31Z","2019-03-29T21:32:07Z"],"total":2},{"week":"14 2019","dates":["2019-04-04T12:53:04Z","2019-04-03T15:16:51Z"],"total":2},{"week":"15 2019","dates":["2019-04-12T14:53:02Z","2019-04-09T14:58:23Z","2019-04-09T12:06:15Z"],"total":3},{"week":"16 2019","dates":["2019-04-17T06:15:29Z"],"total":1},{"week":"17 2019","dates":["2019-04-26T21:17:48Z"],"total":1},{"week":"18 2019","dates":["2019-05-02T03:10:51Z"],"total":1},{"week":"19 2019","dates":["2019-05-10T23:23:52Z","2019-05-09T22:03:04Z","2019-05-08T05:33:25Z","2019-05-06T15:19:36Z"],"total":4},{"week":"20 2019","dates":["2019-05-19T08:03:23Z","2019-05-18T20:28:03Z","2019-05-16T03:58:23Z"],"total":3},{"week":"21 2019","dates":["2019-05-26T15:19:49Z","2019-05-22T10:22:39Z","2019-05-22T09:48:56Z","2019-05-20T16:45:51Z"],"total":4},{"week":"22 2019","dates":["2019-06-02T22:00:28Z"],"total":1},{"week":"23 2019","total":0,"dates":[]},{"week":"24 2019","dates":["2019-06-15T02:53:32Z","2019-06-14T03:00:46Z","2019-06-12T13:30:12Z","2019-06-11T12:48:14Z"],"total":4},{"week":"25 2019","total":0,"dates":[]},{"week":"26 2019","dates":["2019-06-25T14:29:13Z","2019-06-24T23:58:52Z"],"total":2},{"week":"27 2019","total":0,"dates":[]},{"week":"28 2019","total":0,"dates":[]},{"week":"29 2019","total":0,"dates":[]},{"week":"30 2019","dates":["2019-07-24T08:47:57Z"],"total":1},{"week":"31 2019","dates":["2019-07-30T16:48:07Z"],"total":1},{"week":"32 2019","dates":["2019-08-11T14:07:58Z","2019-08-10T20:23:38Z"],"total":2},{"week":"33 2019","dates":["2019-08-14T19:24:35Z","2019-08-14T15:25:00Z"],"total":2},{"week":"34 2019","dates":["2019-08-23T06:12:42Z","2019-08-21T22:34:52Z"],"total":2},{"week":"35 2019","dates":["2019-08-30T15:33:13Z"],"total":1},{"week":"36 2019","dates":["2019-09-03T07:19:58Z"],"total":1},{"week":"37 2019","dates":["2019-09-12T14:53:53Z","2019-09-11T09:40:31Z","2019-09-10T11:29:55Z"],"total":3},{"week":"38 2019","dates":["2019-09-22T12:33:11Z","2019-09-17T20:59:34Z"],"total":2},{"week":"39 2019","dates":["2019-09-27T16:14:13Z","2019-09-26T10:56:24Z","2019-09-23T03:08:25Z"],"total":3},{"week":"40 2019","dates":["2019-10-04T18:51:08Z","2019-10-03T04:53:20Z"],"total":2},{"week":"41 2019","dates":["2019-10-13T11:27:19Z"],"total":1},{"week":"42 2019","dates":["2019-10-19T00:41:03Z","2019-10-16T22:15:43Z","2019-10-16T14:25:00Z"],"total":3},{"week":"43 2019","total":0,"dates":[]},{"week":"44 2019","dates":["2019-10-31T13:30:32Z","2019-10-29T15:41:52Z"],"total":2},{"week":"45 2019","dates":["2019-11-08T20:10:34Z","2019-11-06T15:40:20Z","2019-11-04T14:02:06Z"],"total":3},{"week":"46 2019","dates":["2019-11-11T19:32:06Z"],"total":1},{"week":"47 2019","dates":["2019-11-20T12:30:25Z"],"total":1},{"week":"48 2019","total":0,"dates":[]},{"week":"49 2019","total":0,"dates":[]},{"week":"50 2019","dates":["2019-12-15T11:33:24Z","2019-12-15T01:05:06Z"],"total":2},{"week":"51 2019","dates":["2019-12-18T12:49:07Z"],"total":1},{"week":"52 2019","dates":["2019-12-29T03:13:17Z","2019-12-23T19:12:04Z"],"total":2},{"week":"01 2020","total":0,"dates":[]},{"week":"02 2020","dates":["2020-01-10T06:09:31Z"],"total":1},{"week":"03 2020","total":0,"dates":[]},{"week":"04 2020","total":0,"dates":[]},{"week":"05 2020","dates":["2020-01-31T19:19:53Z","2020-01-29T22:28:34Z","2020-01-29T17:25:24Z","2020-01-28T03:17:02Z"],"total":4},{"week":"06 2020","dates":["2020-02-04T00:41:51Z","2020-02-03T06:51:19Z"],"total":2},{"week":"07 2020","dates":["2020-02-15T14:51:17Z"],"total":1},{"week":"08 2020","total":0,"dates":[]},{"week":"09 2020","dates":["2020-02-28T07:05:49Z","2020-02-25T04:09:26Z"],"total":2},{"week":"10 2020","dates":["2020-03-05T10:33:59Z","2020-03-04T03:24:20Z"],"total":2},{"week":"11 2020","dates":["2020-03-12T00:42:16Z"],"total":1},{"week":"12 2020","total":0,"dates":[]},{"week":"13 2020","dates":["2020-03-25T20:31:10Z","2020-03-24T07:34:05Z","2020-03-23T04:39:38Z"],"total":3},{"week":"14 2020","dates":["2020-04-01T20:12:54Z"],"total":1},{"week":"15 2020","dates":["2020-04-06T20:49:07Z"],"total":1},{"week":"16 2020","dates":["2020-04-17T18:12:05Z","2020-04-16T02:30:34Z","2020-04-13T22:05:39Z"],"total":3},{"week":"17 2020","dates":["2020-04-21T18:02:27Z"],"total":1},{"week":"18 2020","total":0,"dates":[]},{"week":"19 2020","dates":["2020-05-08T12:02:52Z","2020-05-06T20:09:01Z","2020-05-05T15:52:12Z","2020-05-05T01:04:30Z"],"total":4},{"week":"20 2020","dates":["2020-05-16T15:42:55Z"],"total":1},{"week":"21 2020","dates":["2020-05-19T20:40:19Z","2020-05-19T18:18:17Z"],"total":2},{"week":"22 2020","total":0,"dates":[]},{"week":"23 2020","dates":["2020-06-03T19:51:59Z","2020-06-01T20:14:05Z"],"total":2},{"week":"24 2020","total":0,"dates":[]},{"week":"25 2020","dates":["2020-06-20T06:05:27Z","2020-06-18T23:15:09Z"],"total":2},{"week":"26 2020","dates":["2020-06-27T08:01:23Z","2020-06-26T22:00:59Z","2020-06-24T05:09:24Z","2020-06-23T19:19:02Z","2020-06-23T17:21:48Z","2020-06-22T14:22:25Z"],"total":6},{"week":"27 2020","dates":["2020-06-30T23:30:00Z"],"total":1},{"week":"28 2020","dates":["2020-07-08T01:35:31Z"],"total":1},{"week":"29 2020","dates":["2020-07-17T08:43:44Z","2020-07-15T18:42:11Z"],"total":2},{"week":"30 2020","total":0,"dates":[]},{"week":"31 2020","dates":["2020-07-31T23:07:49Z","2020-07-29T17:47:28Z"],"total":2},{"week":"32 2020","dates":["2020-08-04T06:12:06Z"],"total":1},{"week":"33 2020","dates":["2020-08-12T13:57:46Z","2020-08-11T02:17:45Z"],"total":2},{"week":"34 2020","total":0,"dates":[]},{"week":"35 2020","total":0,"dates":[]},{"week":"36 2020","dates":["2020-09-05T11:24:00Z"],"total":1},{"week":"37 2020","dates":["2020-09-08T03:10:20Z","2020-09-07T12:34:11Z"],"total":2},{"week":"38 2020","dates":["2020-09-15T09:40:54Z"],"total":1},{"week":"39 2020","dates":["2020-09-26T08:08:26Z","2020-09-25T08:15:22Z","2020-09-24T10:38:53Z","2020-09-23T23:43:16Z","2020-09-21T20:14:08Z"],"total":5},{"week":"40 2020","dates":["2020-10-02T06:31:45Z","2020-10-01T09:15:29Z","2020-10-01T05:47:20Z"],"total":3},{"week":"41 2020","dates":["2020-10-09T14:46:34Z","2020-10-09T09:42:52Z","2020-10-06T15:10:51Z","2020-10-05T20:15:10Z","2020-10-05T06:01:09Z"],"total":5},{"week":"42 2020","dates":["2020-10-16T18:03:54Z","2020-10-16T17:45:26Z","2020-10-16T16:21:00Z"],"total":3},{"week":"43 2020","dates":["2020-10-23T11:28:05Z","2020-10-22T22:59:26Z","2020-10-22T02:10:54Z"],"total":3},{"week":"44 2020","dates":["2020-11-01T03:01:48Z","2020-10-31T10:05:28Z"],"total":2},{"week":"45 2020","dates":["2020-11-06T22:04:08Z","2020-11-02T22:19:01Z"],"total":2},{"week":"46 2020","dates":["2020-11-10T22:25:24Z"],"total":1},{"week":"47 2020","dates":["2020-11-17T16:22:18Z","2020-11-16T14:49:49Z"],"total":2},{"week":"48 2020","total":0,"dates":[]},{"week":"49 2020","dates":["2020-12-04T09:26:31Z","2020-12-04T06:40:37Z","2020-12-01T14:58:02Z"],"total":3},{"week":"50 2020","dates":["2020-12-08T14:13:28Z"],"total":1},{"week":"51 2020","dates":["2020-12-16T13:11:31Z","2020-12-15T23:01:09Z","2020-12-14T15:37:21Z"],"total":3},{"week":"52 2020","dates":["2020-12-24T11:38:22Z"],"total":1},{"week":"53 2020","dates":["2021-01-03T02:53:27Z","2020-12-28T00:52:03Z"],"total":2},{"week":"01 2021","total":0,"dates":[]},{"week":"02 2021","total":0,"dates":[]},{"week":"03 2021","total":0,"dates":[]},{"week":"04 2021","dates":["2021-01-30T15:07:28Z","2021-01-29T22:26:18Z","2021-01-25T12:22:19Z"],"total":3},{"week":"05 2021","dates":["2021-02-06T17:58:46Z"],"total":1},{"week":"06 2021","dates":["2021-02-14T23:55:47Z","2021-02-13T12:59:45Z","2021-02-11T19:18:39Z","2021-02-09T11:30:40Z"],"total":4},{"week":"07 2021","dates":["2021-02-20T22:39:41Z"],"total":1},{"week":"08 2021","dates":["2021-02-27T21:49:57Z","2021-02-27T03:09:55Z","2021-02-26T20:49:16Z","2021-02-26T07:42:20Z","2021-02-23T19:19:06Z","2021-02-23T10:47:20Z","2021-02-22T20:18:42Z"],"total":7},{"week":"09 2021","dates":["2021-03-06T13:17:45Z","2021-03-01T20:46:25Z"],"total":2},{"week":"10 2021","total":0,"dates":[]},{"week":"11 2021","dates":["2021-03-19T21:34:25Z"],"total":1},{"week":"12 2021","dates":["2021-03-23T03:40:30Z"],"total":1},{"week":"13 2021","dates":["2021-04-03T15:03:47Z","2021-04-02T03:44:15Z"],"total":2},{"week":"14 2021","dates":["2021-04-10T07:34:50Z"],"total":1},{"week":"15 2021","dates":["2021-04-17T09:44:09Z","2021-04-14T08:23:41Z"],"total":2},{"week":"16 2021","dates":["2021-04-20T13:55:22Z"],"total":1},{"week":"17 2021","dates":["2021-05-01T17:27:05Z","2021-04-30T11:38:54Z"],"total":2},{"week":"18 2021","dates":["2021-05-05T10:32:34Z","2021-05-04T11:09:52Z"],"total":2},{"week":"19 2021","dates":["2021-05-15T18:44:39Z","2021-05-13T13:06:48Z","2021-05-13T12:17:06Z"],"total":3},{"week":"20 2021","dates":["2021-05-23T15:19:32Z"],"total":1},{"week":"21 2021","total":0,"dates":[]},{"week":"22 2021","dates":["2021-06-06T14:10:22Z","2021-05-31T09:18:13Z"],"total":2},{"week":"23 2021","dates":["2021-06-11T22:01:54Z","2021-06-07T12:35:30Z"],"total":2},{"week":"24 2021","dates":["2021-06-17T19:59:54Z"],"total":1},{"week":"25 2021","dates":["2021-06-24T19:39:42Z","2021-06-24T17:00:46Z","2021-06-21T19:54:50Z"],"total":3},{"week":"26 2021","dates":["2021-07-04T16:57:25Z","2021-07-04T08:41:19Z","2021-07-02T07:27:36Z","2021-07-01T03:10:03Z","2021-06-29T11:40:46Z","2021-06-28T17:06:18Z","2021-06-28T13:16:40Z"],"total":7},{"week":"27 2021","dates":["2021-07-10T08:54:58Z","2021-07-07T17:01:11Z","2021-07-06T00:55:49Z"],"total":3},{"week":"28 2021","dates":["2021-07-14T16:43:07Z","2021-07-12T20:42:03Z"],"total":2},{"week":"29 2021","dates":["2021-07-22T09:10:05Z","2021-07-21T12:25:48Z"],"total":2},{"week":"30 2021","dates":["2021-07-29T23:28:00Z"],"total":1},{"week":"31 2021","dates":["2021-08-07T08:46:21Z","2021-08-06T14:06:09Z"],"total":2},{"week":"32 2021","total":0,"dates":[]},{"week":"33 2021","dates":["2021-08-22T19:32:20Z","2021-08-18T04:02:00Z","2021-08-17T17:59:05Z"],"total":3},{"week":"34 2021","dates":["2021-08-28T17:32:48Z","2021-08-26T05:23:06Z","2021-08-25T20:57:13Z"],"total":3},{"week":"35 2021","dates":["2021-08-31T14:58:28Z"],"total":1},{"week":"36 2021","dates":["2021-09-11T00:23:27Z","2021-09-07T21:20:10Z"],"total":2},{"week":"37 2021","dates":["2021-09-19T20:37:08Z","2021-09-14T14:03:10Z","2021-09-13T15:42:35Z"],"total":3},{"week":"38 2021","dates":["2021-09-26T21:45:05Z","2021-09-21T20:26:07Z","2021-09-21T15:28:39Z","2021-09-20T20:17:46Z"],"total":4},{"week":"39 2021","dates":["2021-10-02T14:01:42Z","2021-09-30T05:19:00Z","2021-09-28T08:22:53Z","2021-09-27T04:42:09Z"],"total":4},{"week":"40 2021","dates":["2021-10-08T20:51:28Z","2021-10-05T10:43:49Z","2021-10-05T09:12:45Z"],"total":3},{"week":"41 2021","dates":["2021-10-17T13:46:23Z","2021-10-14T07:42:07Z","2021-10-12T16:46:01Z"],"total":3},{"week":"42 2021","dates":["2021-10-24T14:44:36Z","2021-10-23T23:04:35Z","2021-10-21T20:06:54Z","2021-10-20T12:04:43Z","2021-10-19T23:11:29Z","2021-10-19T17:02:44Z","2021-10-18T23:58:25Z","2021-10-18T19:17:44Z"],"total":8}],"labels":["bug","CLA not signed","CLA signed","duplicate","enhancement","governance","in-progress","invalid","question","wontfix"],"newcomer_labels":[],"has_newcomer_labels":false}